cjk6_source_ci_secrets/__init__.py
cjk6_source_ci_secrets/main.py
cjk6_source_ci_secrets-0.0.26.dist-info/LICENSE
cjk6_source_ci_secrets-0.0.26.dist-info/LICENSE.md
cjk6_source_ci_secrets-0.0.26.dist-info/METADATA
cjk6_source_ci_secrets-0.0.26.dist-info/WHEEL
cjk6_source_ci_secrets-0.0.26.dist-info/entry_points.txt
cjk6_source_ci_secrets-0.0.26.dist-info/top_level.txt
cjk6_source_ci_secrets-0.0.26.dist-info/RECORD
