Metadata-Version: 2.1
Name: cjk6-source-ci-secrets
Version: 0.0.26
Summary: A secrets scanner for CI/CD forked from ci_secrets.
Home-page: https://github.com/cjk6-source/ci_secrets
Author: Christian Kang
Author-email: christiankang56@gmail.com
License: UNKNOWN
Platform: UNKNOWN
Classifier: License :: OSI Approved :: Apache Software License
Classifier: Programming Language :: Python :: 3
Classifier: Topic :: Security
Classifier: Topic :: Software Development
Requires-Dist: detect-secrets
Requires-Dist: gitpython
